{
 "figura": {
  "ponto": [
   {
    "p": {
     "x": -0.7395833134651184,
     "y": 0.4018518626689911
    },
    "cor": {
     "r": 250,
     "g": 161,
     "b": 0
    }
   },
   {
    "p": {
     "x": -0.6020833253860474,
     "y": 0.31481480598449707
    },
    "cor": {
     "r": 250,
     "g": 161,
     "b": 0
    }
   },
   {
    "p": {
     "x": -0.39895832538604736,
     "y": 0.42407408356666565
    },
    "cor": {
     "r": 250,
     "g": 161,
     "b": 0
    }
   },
   {
    "p": {
     "x": -0.3010416626930237,
     "y": 0.4296296238899231
    },
    "cor": {
     "r": 250,
     "g": 161,
     "b": 0
    }
   },
   {
    "p": {
     "x": -0.23749999701976776,
     "y": 0.5
    },
    "cor": {
     "r": 250,
     "g": 161,
     "b": 0
    }
   }
  ],
  "linha": [
   {
    "p1": {
     "x": -0.6781250238418579,
     "y": -0.307407408952713
    },
    "p2": {
     "x": -0.33645832538604736,
     "y": 0.3611111044883728
    },
    "cor": {
     "r": 250,
     "g": 161,
     "b": 0
    }
   },
   {
    "p1": {
     "x": -0.815625011920929,
     "y": -0.2222222238779068
    },
    "p2": {
     "x": -0.8843749761581421,
     "y": 0.3222222328186035
    },
    "cor": {
     "r": 250,
     "g": 161,
     "b": 0
    }
   }
  ],
  "triangulo": [
   {
    "p1": {
     "x": -0.5239583253860474,
     "y": -0.40740740299224854
    },
    "p2": {
     "x": -0.5041666626930237,
     "y": -0.20555555820465088
    },
    "p3": {
     "x": -0.31458333134651184,
     "y": -0.34074074029922485
    },
    "cor": {
     "r": 250,
     "g": 161,
     "b": 0
    }
   },
   {
    "p1": {
     "x": -0.706250011920929,
     "y": -0.6574074029922485
    },
    "p2": {
     "x": -0.6781250238418579,
     "y": -0.529629647731781
    },
    "p3": {
     "x": -0.38229167461395264,
     "y": -0.7129629850387573
    },
    "cor": {
     "r": 250,
     "g": 161,
     "b": 0
    }
   }
  ],
  "retangulo": [
   {
    "p1": {
     "x": -0.24062499403953552,
     "y": 0.18888889253139496
    },
    "p2": {
     "x": -0.11562500149011612,
     "y": 0.40925925970077515
    },
    "cor": {
     "r": 250,
     "g": 161,
     "b": 0
    }
   },
   {
    "p1": {
     "x": -0.37812501192092896,
     "y": 0.5370370149612427
    },
    "p2": {
     "x": -0.24583333730697632,
     "y": 0.7444444298744202
    },
    "cor": {
     "r": 250,
     "g": 161,
     "b": 0
    }
   }
  ],
  "circulo": [
   {
    "ponto": {
     "x": -0.22499999403953552,
     "y": -0.5314815044403076
    },
    "raio": 0.1041666641831398,
    "cor": {
     "r": 250,
     "g": 161,
     "b": 0
    }
   },
   {
    "ponto": {
     "x": -0.14895834028720856,
     "y": -0.1944444477558136
    },
    "raio": 0.1041666641831398,
    "cor": {
     "r": 250,
     "g": 161,
     "b": 0
    }
   }
  ],
  "linha poligonal": [
   {
    "ponto": [
     {
      "x": -0.2510416805744171,
      "y": -0.12962962687015533
     },
     {
      "x": -0.5854166746139526,
      "y": 0.11481481790542603
     },
     {
      "x": -0.7427083253860474,
      "y": 0.14259259402751923
     },
     {
      "x": -0.7885416746139526,
      "y": -0.011111111380159855
     },
     {
      "x": -0.7677083611488342,
      "y": -0.07592592388391495
     },
     {
      "x": -0.621874988079071,
      "y": -0.2203703671693802
     }
    ],
    "cor": {
     "r": 250,
     "g": 161,
     "b": 0
    }
   }
  ]
 }
}